in/__init__.py
in/python.py
ravspeak-0.0.1.dist-info/LICENSE
ravspeak-0.0.1.dist-info/METADATA
ravspeak-0.0.1.dist-info/WHEEL
ravspeak-0.0.1.dist-info/top_level.txt
ravspeak-0.0.1.dist-info/RECORD
